llama_index/tools/shopify/__init__.py
llama_index/tools/shopify/base.py
llama_index_tools_shopify-0.4.1.dist-info/METADATA
llama_index_tools_shopify-0.4.1.dist-info/WHEEL
llama_index_tools_shopify-0.4.1.dist-info/licenses/LICENSE
llama_index_tools_shopify-0.4.1.dist-info/RECORD
